[{"latitude":"-23.52082","color":"yellow","longitude":"-46.18541","uf":"SP","tecnologia":"Sobreposição HFC e GPON","name":"Mogi das Cruzes, SP <br> Sobreposição HFC e GPON","cidade":"Mogi das Cruzes"},{"latitude":"-10.239973","color":"yellow","longitude":"-48.355751","uf":"TO","tecnologia":"Sobreposição HFC e GPON","name":"Palmas, TO <br> Sobreposição HFC e GPON","cidade":"Palmas"},{"latitude":"-9.97499","color":"yellow","longitude":"-67.824348","uf":"AC","tecnologia":"Sobreposição HFC e GPON","name":"Rio Branco, AC <br> Sobreposição HFC e GPON","cidade":"Rio Branco"},{"latitude":"-3.118662","color":"yellow","longitude":"-60.02123","uf":"AM","tecnologia":"Sobreposição HFC e GPON","name":"Manaus, AM <br> Sobreposição HFC e GPON","cidade":"Manaus"},{"latitude":"-12.8978","color":"yellow","longitude":"-38.321008","uf":"BA","tecnologia":"Sobreposição HFC e GPON","name":"Lauro de Freitas, BA <br> Sobreposição HFC e GPON","cidade":"Lauro de Freitas"},{"latitude":"-12.97178","color":"yellow","longitude":"-38.501068","uf":"BA","tecnologia":"Sobreposição HFC e GPON","name":"Salvador, BA <br> Sobreposição HFC e GPON","cidade":"Salvador"},{"latitude":"-3.716638","color":"yellow","longitude":"-38.542298","uf":"CE","tecnologia":"Sobreposição HFC e GPON","name":"Fortaleza, CE <br> Sobreposição HFC e GPON","cidade":"Fortaleza"},{"latitude":"-20.263202","color":"yellow","longitude":"-40.416549","uf":"ES","tecnologia":"Sobreposição HFC e GPON","name":"Cariacica, ES <br> Sobreposição HFC e GPON","cidade":"Cariacica"},{"latitude":"-20.121032","color":"yellow","longitude":"-40.307408","uf":"ES","tecnologia":"Sobreposição HFC e GPON","name":"Serra, ES <br> Sobreposição HFC e GPON","cidade":"Serra"},{"latitude":"-20.341705","color":"yellow","longitude":"-40.287458","uf":"ES","tecnologia":"Sobreposição HFC e GPON","name":"Vila Velha, ES <br> Sobreposição HFC e GPON","cidade":"Vila Velha"},{"latitude":"-19.910183","color":"yellow","longitude":"-43.926572","uf":"MG","tecnologia":"Sobreposição HFC e GPON","name":"Belo Horizonte, MG <br> Sobreposição HFC e GPON","cidade":"Belo Horizonte"},{"latitude":"-19.932079","color":"yellow","longitude":"-44.05392","uf":"MG","tecnologia":"Sobreposição HFC e GPON","name":"Contagem, MG <br> Sobreposição HFC e GPON","cidade":"Contagem"},{"latitude":"-20.448589","color":"yellow","longitude":"-54.629463","uf":"MS","tecnologia":"Sobreposição HFC e GPON","name":"Campo Grande, MS <br> Sobreposição HFC e GPON","cidade":"Campo Grande"},{"latitude":"-1.363914","color":"yellow","longitude":"-48.374298","uf":"PA","tecnologia":"Sobreposição HFC e GPON","name":"Ananindeua, PA <br> Sobreposição HFC e GPON","cidade":"Ananindeua"},{"latitude":"-8.010166","color":"yellow","longitude":"-34.854504","uf":"PE","tecnologia":"Sobreposição HFC e GPON","name":"Olinda, PE <br> Sobreposição HFC e GPON","cidade":"Olinda"},{"latitude":"-7.934007","color":"yellow","longitude":"-34.868407","uf":"PE","tecnologia":"Sobreposição HFC e GPON","name":"Paulista, PE <br> Sobreposição HFC e GPON","cidade":"Paulista"},{"latitude":"-8.046658","color":"yellow","longitude":"-34.877065","uf":"PE","tecnologia":"Sobreposição HFC e GPON","name":"Recife, PE <br> Sobreposição HFC e GPON","cidade":"Recife"},{"latitude":"-5.091944","color":"yellow","longitude":"-42.803364","uf":"PI","tecnologia":"Sobreposição HFC e GPON","name":"Teresina, PI <br> Sobreposição HFC e GPON","cidade":"Teresina"},{"latitude":"-25.452535","color":"yellow","longitude":"-49.529026","uf":"PR","tecnologia":"Sobreposição HFC e GPON","name":"Campo Largo, PR <br> Sobreposição HFC e GPON","cidade":"Campo Largo"},{"latitude":"-25.419547","color":"yellow","longitude":"-49.264622","uf":"PR","tecnologia":"Sobreposição HFC e GPON","name":"Curitiba, PR <br> Sobreposição HFC e GPON","cidade":"Curitiba"},{"latitude":"-22.912897","color":"yellow","longitude":"-43.200295","uf":"RJ","tecnologia":"Sobreposição HFC e GPON","name":"Rio de Janeiro, RJ <br> Sobreposição HFC e GPON","cidade":"Rio de Janeiro"},{"latitude":"-5.793567","color":"yellow","longitude":"-35.198604","uf":"RN","tecnologia":"Sobreposição HFC e GPON","name":"Natal, RN <br> Sobreposição HFC e GPON","cidade":"Natal"},{"latitude":"-5.911156","color":"yellow","longitude":"-35.271","uf":"RN","tecnologia":"Sobreposição HFC e GPON","name":"Parnamirim, RN <br> Sobreposição HFC e GPON","cidade":"Parnamirim"},{"latitude":"-8.760772","color":"yellow","longitude":"-63.899902","uf":"RO","tecnologia":"Sobreposição HFC e GPON","name":"Porto Velho, RO <br> Sobreposição HFC e GPON","cidade":"Porto Velho"},{"latitude":"-29.947222","color":"yellow","longitude":"-51.101606","uf":"RS","tecnologia":"Sobreposição HFC e GPON","name":"Cachoeirinha, RS <br> Sobreposição HFC e GPON","cidade":"Cachoeirinha"},{"latitude":"-29.912758","color":"yellow","longitude":"-51.185681","uf":"RS","tecnologia":"Sobreposição HFC e GPON","name":"Canoas, RS <br> Sobreposição HFC e GPON","cidade":"Canoas"},{"latitude":"-29.162905","color":"yellow","longitude":"-51.179161","uf":"RS","tecnologia":"Sobreposição HFC e GPON","name":"Caxias do Sul, RS <br> Sobreposição HFC e GPON","cidade":"Caxias do Sul"},{"latitude":"-29.222689","color":"yellow","longitude":"-51.341853","uf":"RS","tecnologia":"Sobreposição HFC e GPON","name":"Farroupilha, RS <br> Sobreposição HFC e GPON","cidade":"Farroupilha"},{"latitude":"-29.687548","color":"yellow","longitude":"-51.132828","uf":"RS","tecnologia":"Sobreposição HFC e GPON","name":"Novo Hamburgo, RS <br> Sobreposição HFC e GPON","cidade":"Novo Hamburgo"},{"latitude":"-30.031771","color":"yellow","longitude":"-51.206533","uf":"RS","tecnologia":"Sobreposição HFC e GPON","name":"Porto Alegre, RS <br> Sobreposição HFC e GPON","cidade":"Porto Alegre"},{"latitude":"-32.034875","color":"yellow","longitude":"-52.10705","uf":"RS","tecnologia":"Sobreposição HFC e GPON","name":"Rio Grande, RS <br> Sobreposição HFC e GPON","cidade":"Rio Grande"},{"latitude":"-26.304497","color":"yellow","longitude":"-48.848675","uf":"SC","tecnologia":"Sobreposição HFC e GPON","name":"Joinville, SC <br> Sobreposição HFC e GPON","cidade":"Joinville"},{"latitude":"-22.73736","color":"yellow","longitude":"-47.333119","uf":"SP","tecnologia":"Sobreposição HFC e GPON","name":"Americana, SP <br> Sobreposição HFC e GPON","cidade":"Americana"},{"latitude":"-21.784511","color":"yellow","longitude":"-48.178014","uf":"SP","tecnologia":"Sobreposição HFC e GPON","name":"Araraquara, SP <br> Sobreposição HFC e GPON","cidade":"Araraquara"},{"latitude":"-22.357238","color":"yellow","longitude":"-47.384235","uf":"SP","tecnologia":"Sobreposição HFC e GPON","name":"Araras, SP <br> Sobreposição HFC e GPON","cidade":"Araras"},{"latitude":"-23.117059","color":"yellow","longitude":"-46.556262","uf":"SP","tecnologia":"Sobreposição HFC e GPON","name":"Atibaia, SP <br> Sobreposição HFC e GPON","cidade":"Atibaia"},{"latitude":"-22.905346","color":"yellow","longitude":"-47.06595","uf":"SP","tecnologia":"Sobreposição HFC e GPON","name":"Campinas, SP <br> Sobreposição HFC e GPON","cidade":"Campinas"},{"latitude":"-23.681347","color":"yellow","longitude":"-46.62052","uf":"SP","tecnologia":"Sobreposição HFC e GPON","name":"Diadema, SP <br> Sobreposição HFC e GPON","cidade":"Diadema"},{"latitude":"-23.042822","color":"yellow","longitude":"-47.368153","uf":"SP","tecnologia":"Sobreposição HFC e GPON","name":"Elias Fausto, SP <br> Sobreposição HFC e GPON","cidade":"Elias Fausto"},{"latitude":"-20.53523","color":"yellow","longitude":"-47.403861","uf":"SP","tecnologia":"Sobreposição HFC e GPON","name":"Franca, SP <br> Sobreposição HFC e GPON","cidade":"Franca"},{"latitude":"-23.453758","color":"yellow","longitude":"-46.533347","uf":"SP","tecnologia":"Sobreposição HFC e GPON","name":"Guarulhos, SP <br> Sobreposição HFC e GPON","cidade":"Guarulhos"},{"latitude":"-23.081591","color":"yellow","longitude":"-47.210093","uf":"SP","tecnologia":"Sobreposição HFC e GPON","name":"Indaiatuba, SP <br> Sobreposição HFC e GPON","cidade":"Indaiatuba"},{"latitude":"-23.254397","color":"yellow","longitude":"-47.292688","uf":"SP","tecnologia":"Sobreposição HFC e GPON","name":"Itu, SP <br> Sobreposição HFC e GPON","cidade":"Itu"},{"latitude":"-23.53239","color":"yellow","longitude":"-46.791555","uf":"SP","tecnologia":"Sobreposição HFC e GPON","name":"Osasco, SP <br> Sobreposição HFC e GPON","cidade":"Osasco"},{"latitude":"-22.733801","color":"yellow","longitude":"-47.647612","uf":"SP","tecnologia":"Sobreposição HFC e GPON","name":"Piracicaba, SP <br> Sobreposição HFC e GPON","cidade":"Piracicaba"},{"latitude":"-24.008378","color":"yellow","longitude":"-46.412057","uf":"SP","tecnologia":"Sobreposição HFC e GPON","name":"Praia Grande, SP <br> Sobreposição HFC e GPON","cidade":"Praia Grande"},{"latitude":"-22.398378","color":"yellow","longitude":"-47.554632","uf":"SP","tecnologia":"Sobreposição HFC e GPON","name":"Rio Claro, SP <br> Sobreposição HFC e GPON","cidade":"Rio Claro"},{"latitude":"-23.953543","color":"yellow","longitude":"-46.335042","uf":"SP","tecnologia":"Sobreposição HFC e GPON","name":"Santos, SP <br> Sobreposição HFC e GPON","cidade":"Santos"},{"latitude":"-23.496886","color":"yellow","longitude":"-47.445073","uf":"SP","tecnologia":"Sobreposição HFC e GPON","name":"Sorocaba, SP <br> Sobreposição HFC e GPON","cidade":"Sorocaba"},{"latitude":"-22.969805","color":"yellow","longitude":"-46.997367","uf":"SP","tecnologia":"Sobreposição HFC e GPON","name":"Valinhos, SP <br> Sobreposição HFC e GPON","cidade":"Valinhos"},{"latitude":"-23.54459","color":"yellow","longitude":"-47.438753","uf":"SP","tecnologia":"Sobreposição HFC e GPON","name":"Votorantim, SP <br> Sobreposição HFC e GPON","cidade":"Votorantim"}]
